fpzip.cp310-win_amd64.pyd
fpzip-1.2.5.dist-info/licenses/AUTHORS
fpzip-1.2.5.dist-info/licenses/LICENSE
fpzip-1.2.5.dist-info/METADATA
fpzip-1.2.5.dist-info/WHEEL
fpzip-1.2.5.dist-info/pbr.json
fpzip-1.2.5.dist-info/top_level.txt
fpzip-1.2.5.dist-info/RECORD
