Metadata-Version: 2.4
Name: fpzip
Version: 1.2.5
Summary: Numpy wrapper for fpzip algorithm (P. Lindstrom & M. Isenburg, 2006)
Home-page: https://github.com/seung-lab/fpzip/
Author: William Silversmith
Author-email: ws9@princeton.edu
License: None
Classifier: Intended Audience :: Developers
Classifier: Development Status :: 5 - Production/Stable
Classifier: Programming Language :: Python :: 3
Classifier: Programming Language :: Python :: 3.7
Classifier: Programming Language :: Python :: 3.8
Classifier: Programming Language :: Python :: 3.9
Classifier: Programming Language :: Python :: 3.10
Classifier: Programming Language :: Python :: 3.11
Classifier: Topic :: Scientific/Engineering
Classifier: Topic :: System :: Archiving :: Compression
Requires-Python: >=3.8,<4.0
License-File: LICENSE
License-File: AUTHORS
Requires-Dist: numpy
Dynamic: author
Dynamic: author-email
Dynamic: classifier
Dynamic: description
Dynamic: description-content-type
Dynamic: home-page
Dynamic: license
Dynamic: license-file
Dynamic: requires-dist
Dynamic: requires-python
Dynamic: summary
